askui/__init__.py
askui/agent.py
askui/agent_base.py
askui/android_agent.py
askui/container.py
askui/custom_agent.py
askui/data_extractor.py
askui/exceptions.py
askui/reporting.py
askui/retry.py
askui/settings.py
askui/web_agent.py
askui/web_testing_agent.py
askui/chat/__init__.py
askui/chat/__main__.py
askui/chat/api/__init__.py
askui/chat/api/app.py
askui/chat/api/dependencies.py
askui/chat/api/models.py
askui/chat/api/settings.py
askui/chat/api/utils.py
askui/chat/api/assistants/__init__.py
askui/chat/api/assistants/dependencies.py
askui/chat/api/assistants/models.py
askui/chat/api/assistants/orms.py
askui/chat/api/assistants/router.py
askui/chat/api/assistants/service.py
askui/chat/api/db/__init__.py
askui/chat/api/db/engine.py
askui/chat/api/db/queries.py
askui/chat/api/db/session.py
askui/chat/api/db/orm/__init__.py
askui/chat/api/db/orm/base.py
askui/chat/api/db/orm/types.py
askui/chat/api/files/__init__.py
askui/chat/api/files/dependencies.py
askui/chat/api/files/models.py
askui/chat/api/files/orms.py
askui/chat/api/files/router.py
askui/chat/api/files/service.py
askui/chat/api/health/__init__.py
askui/chat/api/health/router.py
askui/chat/api/mcp_clients/__init__.py
askui/chat/api/mcp_clients/dependencies.py
askui/chat/api/mcp_clients/manager.py
askui/chat/api/mcp_configs/__init__.py
askui/chat/api/mcp_configs/dependencies.py
askui/chat/api/mcp_configs/models.py
askui/chat/api/mcp_configs/orms.py
askui/chat/api/mcp_configs/router.py
askui/chat/api/mcp_configs/service.py
askui/chat/api/mcp_servers/__init__.py
askui/chat/api/mcp_servers/android.py
askui/chat/api/mcp_servers/android_setup_doc.py
askui/chat/api/mcp_servers/computer.py
askui/chat/api/mcp_servers/testing.py
askui/chat/api/mcp_servers/utility.py
askui/chat/api/messages/__init__.py
askui/chat/api/messages/chat_history_manager.py
askui/chat/api/messages/dependencies.py
askui/chat/api/messages/models.py
askui/chat/api/messages/orms.py
askui/chat/api/messages/router.py
askui-0.23.0.dist-info/METADATA
askui-0.23.0.dist-info/WHEEL
askui-0.23.0.dist-info/licenses/LICENSE
askui-0.23.0.dist-info/RECORD
