Metadata-Version: 2.4
Name: askui
Version: 0.23.0
Summary: Automate computer tasks in Python
Author-email: askui GmbH <info@askui.com>
License: MIT
License-File: LICENSE
Requires-Python: <3.14,>=3.10
Requires-Dist: aiofiles>=24.1.0
Requires-Dist: anthropic>=0.72.0
Requires-Dist: anyio==4.10.0
Requires-Dist: apscheduler==4.0.0a6
Requires-Dist: asyncer==0.0.8
Requires-Dist: bson>=0.5.10
Requires-Dist: fastapi>=0.115.12
Requires-Dist: fastmcp>=2.3.0
Requires-Dist: filetype>=1.2.0
Requires-Dist: google-genai>=1.20.0
Requires-Dist: gradio-client>=1.4.3
Requires-Dist: grpcio>=1.73.1
Requires-Dist: httpx>=0.28.1
Requires-Dist: jinja2>=3.1.4
Requires-Dist: jsonref>=1.1.0
Requires-Dist: markitdown[docx,xls,xlsx]>=0.1.2
Requires-Dist: openai>=1.61.1
Requires-Dist: pillow>=11.0.0
Requires-Dist: protobuf>=6.31.1
Requires-Dist: py-machineid>=0.7.0
Requires-Dist: pydantic-settings>=2.9.1
Requires-Dist: pydantic>=2.11.0
Requires-Dist: pyperclip>=1.9.0
Requires-Dist: python-dateutil>=2.9.0.post0
Requires-Dist: requests>=2.32.3
Requires-Dist: segment-analytics-python>=2.3.4
Requires-Dist: sqlalchemy[mypy]>=2.0.44
Requires-Dist: tenacity>=9.1.2
Provides-Extra: all
Requires-Dist: alembic>=1.16.5; extra == 'all'
Requires-Dist: anthropic[bedrock]>=0.72.0; extra == 'all'
Requires-Dist: anthropic[vertex]>=0.72.0; extra == 'all'
Requires-Dist: anyio>=4.10.0; extra == 'all'
Requires-Dist: asgi-correlation-id>=4.3.4; extra == 'all'
Requires-Dist: google-cloud-aiplatform>=1.122.0; extra == 'all'
Requires-Dist: mss>=10.0.0; extra == 'all'
Requires-Dist: opentelemetry-api>=1.38.0; extra == 'all'
Requires-Dist: opentelemetry-exporter-otlp-proto-http>=1.38.0; extra == 'all'
Requires-Dist: opentelemetry-instrumentation-fastapi>=0.59b0; extra == 'all'
Requires-Dist: opentelemetry-instrumentation-httpx>=0.59b0; extra == 'all'
Requires-Dist: opentelemetry-instrumentation-sqlalchemy>=0.59b0; extra == 'all'
Requires-Dist: opentelemetry-sdk>=1.38.0; extra == 'all'
Requires-Dist: playwright>=1.41.0; extra == 'all'
Requires-Dist: prometheus-fastapi-instrumentator>=7.1.0; extra == 'all'
Requires-Dist: pure-python-adb>=0.3.0.dev0; extra == 'all'
Requires-Dist: pynput>=1.8.1; extra == 'all'
Requires-Dist: sqlalchemy>=2.0.43; extra == 'all'
Requires-Dist: starlette-context>=0.4.0; extra == 'all'
Requires-Dist: structlog>=25.4.0; extra == 'all'
Requires-Dist: uvicorn>=0.34.3; extra == 'all'
Provides-Extra: android
Requires-Dist: pure-python-adb>=0.3.0.dev0; extra == 'android'
Provides-Extra: bedrock
Requires-Dist: anthropic[bedrock]>=0.72.0; extra == 'bedrock'
Provides-Extra: chat
Requires-Dist: alembic>=1.16.5; extra == 'chat'
Requires-Dist: anyio>=4.10.0; extra == 'chat'
Requires-Dist: asgi-correlation-id>=4.3.4; extra == 'chat'
Requires-Dist: opentelemetry-api>=1.38.0; extra == 'chat'
Requires-Dist: opentelemetry-exporter-otlp-proto-http>=1.38.0; extra == 'chat'
Requires-Dist: opentelemetry-instrumentation-fastapi>=0.59b0; extra == 'chat'
Requires-Dist: opentelemetry-instrumentation-httpx>=0.59b0; extra == 'chat'
Requires-Dist: opentelemetry-instrumentation-sqlalchemy>=0.59b0; extra == 'chat'
Requires-Dist: opentelemetry-sdk>=1.38.0; extra == 'chat'
Requires-Dist: playwright>=1.41.0; extra == 'chat'
Requires-Dist: prometheus-fastapi-instrumentator>=7.1.0; extra == 'chat'
Requires-Dist: pure-python-adb>=0.3.0.dev0; extra == 'chat'
Requires-Dist: sqlalchemy>=2.0.43; extra == 'chat'
Requires-Dist: starlette-context>=0.4.0; extra == 'chat'
Requires-Dist: structlog>=25.4.0; extra == 'chat'
Requires-Dist: uvicorn>=0.34.3; extra == 'chat'
Provides-Extra: pynput
Requires-Dist: mss>=10.0.0; extra == 'pynput'
Requires-Dist: pynput>=1.8.1; extra == 'pynput'
Provides-Extra: vertex
Requires-Dist: anthropic[vertex]>=0.72.0; extra == 'vertex'
Requires-Dist: google-cloud-aiplatform>=1.122.0; extra == 'vertex'
Provides-Extra: web
Requires-Dist: playwright>=1.41.0; extra == 'web'
